pyqueue_celery_processor/__init__.py
pyqueue_celery_processor/client.py
pyqueue_celery_processor/consumer.py
pyqueue_celery_processor-0.0.6.dist-info/LICENSE
pyqueue_celery_processor-0.0.6.dist-info/METADATA
pyqueue_celery_processor-0.0.6.dist-info/WHEEL
pyqueue_celery_processor-0.0.6.dist-info/top_level.txt
pyqueue_celery_processor-0.0.6.dist-info/RECORD
