Metadata-Version: 2.1
Name: pyqueue-celery-processor
Version: 0.0.6
Summary: Python queue to process celery tasks.
Home-page: https://gitlab.com/fampay-oss/pyqueue-celery-processor
Author: Fampay
Author-email: tech@fampay.in
Maintainer: Fampay
Maintainer-email: tech@fampay.in
License: MIT License
Classifier: Development Status :: 5 - Production/Stable
Classifier: Intended Audience :: Developers
Classifier: License :: OSI Approved :: MIT License
Classifier: Operating System :: OS Independent
Classifier: Programming Language :: Python
Classifier: Programming Language :: Python :: 2
Classifier: Programming Language :: Python :: 2.7
Classifier: Programming Language :: Python :: 3
Classifier: Programming Language :: Python :: 3.2
Classifier: Programming Language :: Python :: 3.3
Classifier: Programming Language :: Python :: 3.4
Classifier: Programming Language :: Python :: 3.5
Classifier: Programming Language :: Python :: 3.6
Classifier: Programming Language :: Python :: 3.7
Classifier: Programming Language :: Python :: 3.8
License-File: LICENSE
